modulecmd/__init__.py
modulecmd/_modulecmd.py
modulecmd-1.1.3.dist-info/LICENSE
modulecmd-1.1.3.dist-info/METADATA
modulecmd-1.1.3.dist-info/WHEEL
modulecmd-1.1.3.dist-info/top_level.txt
modulecmd-1.1.3.dist-info/zip-safe
modulecmd-1.1.3.dist-info/RECORD
