Metadata-Version: 2.1
Name: modulecmd
Version: 1.1.3
Summary: modular wrapper support for environment modules
Home-page: https://github.com/jeffee47/modulecmd
Author: Jeff Kiser
Author-email: jkiser@synopsys.com
License: MIT License
Keywords: environment,modules,modulecmd
Platform: UNKNOWN
Classifier: Operating System :: POSIX
Classifier: Operating System :: MacOS :: MacOS X
Classifier: Programming Language :: Python
Classifier: Programming Language :: Python :: 3
Requires-Python: >=2.7
